[
  {
    "id": 0,
    "name": "Европа Плюс",
    "short": "Europa\nPlus",
    "streamUrl": "https://hls-01-regions.emgsound.ru/11_msk/112/playlist.m3u8",
    "color": ["#1a1060", "#3b1fa3"],
    "flag": "🇷🇺"
  },
  {
    "id": 1,
    "name": "Sea FM",
    "short": "Sea FM",
    "streamUrl": "https://s3.myradiostream.com/4976/listen.mp3",
    "color": ["#0a2a0a", "#1a6b1a"],
    "flag": "🇫🇮"
  },
  {
    "id": 2,
    "name": "Antena1",
    "short": "Antena1",
    "streamUrl": "https://antenaone.crossradio.com.br/stream/1",
    "color": ["#2a0a10", "#8b1a2a"],
    "flag": "🇧🇷"
  },
  {
    "id": 3,
    "name": "Авторадио",
    "short": "АВТО\nРАДИО",
    "streamUrl": "https://autoradio.hostingradio.ru:8052/autoradio128.mp3",
    "color": ["#0a1a30", "#1a4a8b"],
    "flag": "🇷🇺"
  },
  {
    "id": 4,
    "name": "Радио Маяк",
    "short": "МАЯК",
    "streamUrl": "https://icecast.vgtrk.cdnvideo.ru/mayak_live",
    "color": ["#1a0a30", "#5b1a8b"],
    "flag": "🇷🇺"
  },
  {
    "id": 5,
    "name": "BBC Radio 1",
    "short": "BBC\nR1",
    "streamUrl": "https://stream.live.vc.bbcmedia.co.uk/bbc_radio_one",
    "color": ["#1a0a0a", "#cc1111"],
    "flag": "🇬🇧"
  },
  {
    "id": 7,
    "name": "NRJ",
    "short": "NRJ",
    "streamUrl": "https://scdn.nrjaudio.fm/audio1/fr/40081/mp3_128.mp3",
    "color": ["#1a1000", "#cc8800"],
    "flag": "🇫🇷"
  }
]
